pysanity/__init__.py
pysanity/adapters.py
pysanity/checks.py
pysanity/proxy.py
pysanity/snippets.py
pysanity/util.py
pysanity-0.0.1.dist-info/DESCRIPTION.rst
pysanity-0.0.1.dist-info/METADATA
pysanity-0.0.1.dist-info/RECORD
pysanity-0.0.1.dist-info/WHEEL
pysanity-0.0.1.dist-info/metadata.json
pysanity-0.0.1.dist-info/pbr.json
pysanity-0.0.1.dist-info/top_level.txt
