Metadata-Version: 2.0
Name: pysanity
Version: 0.0.1
Summary: Emulates sanity for other people's dirty ass non-pep compliant code via only the /dirtiest/ of means.
Home-page: https://github.com/akatrevorjay/pysanity
Author: Trevor Joynson
Author-email: github@skywww.net
License: GPL
Keywords: magic
Requires-Dist: wrapt
